pythonz_pipe-0.1.1.dist-info/METADATA
pythonz_pipe-0.1.1.dist-info/WHEEL
pythonz_pipe/__init__.py
pythonz_pipe-0.1.1.dist-info/RECORD
