Metadata-Version: 2.1
Name: pythonz_pipe
Version: 0.1.1
Summary: pipe implementation of pythonz
Author-Email: Yuichiro Smith <yu-ichiro@s3i7h.com>
License: MIT
Requires-Python: >=3.8
Requires-Dist: pythonz_symbol>=0.1.0
